{"nodes": [{"id": "frontend_src_utils_api_js", "label": "api.js", "file_type": "code", "source_file": "frontend\\src\\utils\\api.js", "source_location": "L1"}, {"id": "api_apiurl", "label": "apiUrl()", "file_type": "code", "source_file": "frontend\\src\\utils\\api.js", "source_location": "L18"}, {"id": "api_authheaders", "label": "authHeaders()", "file_type": "code", "source_file": "frontend\\src\\utils\\api.js", "source_location": "L23"}, {"id": "api_apifetch", "label": "apiFetch()", "file_type": "code", "source_file": "frontend\\src\\utils\\api.js", "source_location": "L28"}, {"id": "api_apiget", "label": "apiGet()", "file_type": "code", "source_file": "frontend\\src\\utils\\api.js", "source_location": "L39"}, {"id": "api_apipost", "label": "apiPost()", "file_type": "code", "source_file": "frontend\\src\\utils\\api.js", "source_location": "L46"}, {"id": "api_apiput", "label": "apiPut()", "file_type": "code", "source_file": "frontend\\src\\utils\\api.js", "source_location": "L58"}], "edges": [{"source": "frontend_src_utils_api_js", "target": "api_apiurl", "relation": "contains", "confidence": "EXTRACTED", "source_file": "frontend\\src\\utils\\api.js", "source_location": "L18", "weight": 1.0}, {"source": "frontend_src_utils_api_js", "target": "api_authheaders", "relation": "contains", "confidence": "EXTRACTED", "source_file": "frontend\\src\\utils\\api.js", "source_location": "L23", "weight": 1.0}, {"source": "frontend_src_utils_api_js", "target": "api_apifetch", "relation": "contains", "confidence": "EXTRACTED", "source_file": "frontend\\src\\utils\\api.js", "source_location": "L28", "weight": 1.0}, {"source": "frontend_src_utils_api_js", "target": "api_apiget", "relation": "contains", "confidence": "EXTRACTED", "source_file": "frontend\\src\\utils\\api.js", "source_location": "L39", "weight": 1.0}, {"source": "frontend_src_utils_api_js", "target": "api_apipost", "relation": "contains", "confidence": "EXTRACTED", "source_file": "frontend\\src\\utils\\api.js", "source_location": "L46", "weight": 1.0}, {"source": "frontend_src_utils_api_js", "target": "api_apiput", "relation": "contains", "confidence": "EXTRACTED", "source_file": "frontend\\src\\utils\\api.js", "source_location": "L58", "weight": 1.0}, {"source": "api_apifetch", "target": "api_apiurl", "relation": "calls", "confidence": "EXTRACTED", "source_file": "frontend\\src\\utils\\api.js", "source_location": "L29", "weight": 1.0}, {"source": "api_apifetch", "target": "api_authheaders", "relation": "calls", "confidence": "EXTRACTED", "source_file": "frontend\\src\\utils\\api.js", "source_location": "L33", "weight": 1.0}, {"source": "api_apiget", "target": "api_apifetch", "relation": "calls", "confidence": "EXTRACTED", "source_file": "frontend\\src\\utils\\api.js", "source_location": "L40", "weight": 1.0}, {"source": "api_apipost", "target": "api_apifetch", "relation": "calls", "confidence": "EXTRACTED", "source_file": "frontend\\src\\utils\\api.js", "source_location": "L47", "weight": 1.0}, {"source": "api_apiput", "target": "api_apifetch", "relation": "calls", "confidence": "EXTRACTED", "source_file": "frontend\\src\\utils\\api.js", "source_location": "L59", "weight": 1.0}]}